moondream_mcp/__init__.py
moondream_mcp/config.py
moondream_mcp/models.py
moondream_mcp/moondream.py
moondream_mcp/py.typed
moondream_mcp/server.py
moondream_mcp/validation.py
moondream_mcp/scripts/__init__.py
moondream_mcp/scripts/setup_claude_desktop.py
moondream_mcp/tools/__init__.py
moondream_mcp/tools/utils.py
moondream_mcp/tools/vision.py
moondream_mcp-1.0.2.dist-info/licenses/LICENSE
moondream_mcp-1.0.2.dist-info/METADATA
moondream_mcp-1.0.2.dist-info/WHEEL
moondream_mcp-1.0.2.dist-info/entry_points.txt
moondream_mcp-1.0.2.dist-info/top_level.txt
moondream_mcp-1.0.2.dist-info/RECORD
